{
    "app-id" : "ca.andyholmes.Valent.Devel",
    "runtime" : "org.gnome.Platform",
    "runtime-version" : "master",
    "sdk" : "org.gnome.Sdk",
    "command" : "valent",
    "finish-args" : [
        "--allow=devel",
        "--device=dri",
        "--env=PULSE_PROP_media.category=Manager",
        "--filesystem=xdg-download",
        "--filesystem=xdg-run/gvfsd",
        "--own-name=org.mpris.MediaPlayer2.Valent",
        "--share=ipc",
        "--share=network",
        "--socket=fallback-x11",
        "--socket=pulseaudio",
        "--socket=session-bus",
        "--socket=ssh-auth",
        "--socket=wayland",
        "--system-talk-name=org.freedesktop.Avahi",
        "--system-talk-name=org.freedesktop.hostname1",
        "--system-talk-name=org.freedesktop.login1",
        "--system-talk-name=org.freedesktop.ModemManager1",
        "--system-talk-name=org.freedesktop.UPower",
        "--talk-name=org.a11y.Bus",
        "--talk-name=org.freedesktop.DBus",
        "--talk-name=org.freedesktop.Flatpak",
        "--talk-name=org.gnome.evolution.dataserver.AddressBook10",
        "--talk-name=org.gnome.evolution.dataserver.Sources5",
        "--talk-name=org.gnome.evolution.dataserver.Subprocess.Backend.*",
        "--talk-name=org.gnome.Mutter.RemoteDesktop",
        "--talk-name=org.gnome.OnlineAccounts",
        "--talk-name=org.gtk.vfs.*",
        "--talk-name=org.mpris.MediaPlayer2.*"
    ],
    "add-extensions" : {
        "ca.andyholmes.Valent.Plugin" : {
            "version" : "master",
            "directory" : "extensions",
            "add-ld-path" : "lib",
            "merge-dirs" : "lib/valent/plugins",
            "subdirectories" : true,
            "no-autodownload" : true,
            "autodelete" : true
        }
    },
    "cleanup" : [
        "/libexec",
        "/man",
        "/share/man",
        "*.la",
        "*.a"
    ],
    "modules" : [
        {
            "name" : "intltool",
            "cleanup" : [
                "*"
            ],
            "sources" : [
                {
                    "type" : "archive",
                    "url" : "https://launchpad.net/intltool/trunk/0.51.0/+download/intltool-0.51.0.tar.gz",
                    "sha256" : "67c74d94196b153b774ab9f89b2fa6c6ba79352407037c8c14d5aeb334e959cd"
                }
            ]
        },
        {
            "name" : "libical",
            "buildsystem" : "cmake-ninja",
            "cleanup" : [
                "/lib/cmake"
            ],
            "config-opts" : [
                "-DCMAKE_INSTALL_LIBDIR:PATH=/app/lib",
                "-DBUILD_SHARED_LIBS:BOOL=ON",
                "-DGOBJECT_INTROSPECTION:BOOL=ON",
                "-DICAL_BUILD_DOCS:BOOL=OFF",
                "-DICAL_GLIB_VAPI:BOOL=ON",
                "-DICAL_GLIB:BOOL=ON"
            ],
            "sources" : [
                {
                    "type" : "git",
                    "url" : "https://github.com/libical/libical.git",
                    "branch" : "master"
                }
            ]
        },
        {
            "name" : "evolution-data-server",
            "buildsystem" : "cmake-ninja",
            "cleanup" : [
                "/etc",
                "/lib/cmake",
                "/lib/evolution-data-server/*-backends",
                "/libexec",
                "/share/applications",
                "/share/dbus-1/services",
                "/share/GConf",
                "/systemd"
            ],
            "config-opts" : [
                "-DCMAKE_BUILD_TYPE=Release",
                "-DENABLE_DOT_LOCKING=OFF",
                "-DENABLE_CANBERRA=OFF",
                "-DENABLE_GTK=OFF",
                "-DENABLE_GTK4=OFF",
                "-DENABLE_GOA=OFF",
                "-DENABLE_GOOGLE=OFF",
                "-DENABLE_OAUTH2=OFF",
                "-DENABLE_VALA_BINDINGS=ON",
                "-DENABLE_WEATHER=OFF",
                "-DENABLE_OAUTH2_WEBKITGTK4=OFF",
                "-DWITH_OPENLDAP=OFF",
                "-DWITH_LIBDB=OFF",
                "-DENABLE_INTROSPECTION=ON",
                "-DENABLE_INSTALLED_TESTS=OFF",
                "-DENABLE_GTK_DOC=OFF",
                "-DENABLE_EXAMPLES=OFF",
                "-DWITH_SYSTEMDUSERUNITDIR=OFF",
                "-DWITH_DBUS_SERVICE_DIR=OFF"
            ],
            "sources" : [
                {
                    "type" : "git",
                    "url" : "https://gitlab.gnome.org/GNOME/evolution-data-server.git",
                    "branch" : "master"
                }
            ]
        },
        {
            "name" : "libpeas",
            "buildsystem" : "meson",
            "builddir" : true,
            "cleanup" : [
                "/bin/*",
                "/lib/peas-demo",
                "/lib/libpeas-gtk*",
                "/share/icons"
            ],
            "config-opts" : [
                "-Dpython3=true",
                "-Dintrospection=true",
                "-Ddemos=false",
                "-Dglade_catalog=false",
                "-Dwidgetry=false"
            ],
            "sources" : [
                {
                    "type" : "git",
                    "url" : "https://gitlab.gnome.org/GNOME/libpeas.git",
                    "branch" : "1.36"
                }
            ]
        },
        {
            "name" : "libportal",
            "buildsystem" : "meson",
            "builddir" : true,
            "config-opts" : [
                "-Dbackends=gtk4",
                "-Ddocs=false",
                "-Dintrospection=false",
                "-Dvapi=false"
            ],
            "sources" : [
                {
                    "type" : "git",
                    "url" : "https://github.com/flatpak/libportal.git",
                    "commit" : "13df0b887a7eb7b0f9b14069561a41f62e813155",
                    "tag" : "0.6"
                }
            ]
        },
        {
            "name" : "sysprof",
            "buildsystem" : "meson",
            "builddir" : true,
            "config-opts" : [
                "--buildtype=debugoptimized",
                "--libdir=/app/lib",
                "-Dgtk=false",
                "-Dsysprofd=host"
            ],
            "cleanup" : [
                "/bin/*",
                "/libexec/sysprof",
                "/share/appdata",
                "/share/applications",
                "/share/metainfo",
                "/share/mime/packages"
            ],
            "sources" : [
                {
                    "type" : "git",
                    "url" : "https://gitlab.gnome.org/GNOME/sysprof.git"
                }
            ]
        },
        "ca.andyholmes.Valent.Tests.json",
        {
            "name" : "valent",
            "buildsystem" : "meson",
            "builddir" : true,
            "config-opts" : [
                "--prefix=/app",
                "--buildtype=debugoptimized",
                "-Dprofile=devel",
                "-Dtests=true",
                "-Dtracing=true"
            ],
            "post-install" : [
                "install -d /app/extensions"
            ],
            "sources" : [
                {
                    "type" : "dir",
                    "path" : "../../"
                }
            ]
        }
    ]
}
